curlwright/__init__.py
curlwright/cli.py
curlwright/main.py
curlwright-2.0.0.dist-info/licenses/LICENSE
src/__init__.py
src/cli.py
src/core/__init__.py
src/core/browser_manager.py
src/core/request_executor.py
src/parsers/__init__.py
src/parsers/curl_parser.py
src/utils/__init__.py
src/utils/cookie_manager.py
src/utils/logger.py
curlwright-2.0.0.dist-info/METADATA
curlwright-2.0.0.dist-info/WHEEL
curlwright-2.0.0.dist-info/entry_points.txt
curlwright-2.0.0.dist-info/top_level.txt
curlwright-2.0.0.dist-info/RECORD
