Metadata-Version: 2.4
Name: curlwright
Version: 2.0.0
Summary: Cloudflare bypass tool using Playwright for curl requests
Home-page: https://github.com/seifreed/Curlwright
Author: Marc Rivero
Author-email: Marc Rivero <mriverolopez@gmail.com>
License: MIT
Project-URL: Homepage, https://github.com/seifreed/Curlwright
Project-URL: Documentation, https://github.com/seifreed/Curlwright#readme
Project-URL: Repository, https://github.com/seifreed/Curlwright
Project-URL: Issues, https://github.com/seifreed/Curlwright/issues
Keywords: cloudflare,bypass,playwright,curl,web-scraping,automation,browser-automation,turnstile
Classifier: Development Status :: 4 - Beta
Classifier: Intended Audience :: Developers
Classifier: Intended Audience :: System Administrators
Classifier: Topic :: Software Development :: Libraries :: Python Modules
Classifier: Topic :: Internet :: WWW/HTTP
Classifier: Topic :: Software Development :: Testing
Classifier: License :: OSI Approved :: MIT License
Classifier: Operating System :: OS Independent
Classifier: Programming Language :: Python :: 3
Classifier: Programming Language :: Python :: 3.9
Classifier: Programming Language :: Python :: 3.10
Classifier: Programming Language :: Python :: 3.11
Classifier: Programming Language :: Python :: 3.12
Requires-Python: >=3.9
License-File: LICENSE
Requires-Dist: playwright>=1.40.0
Requires-Dist: asyncio>=3.4.3
Provides-Extra: dev
Requires-Dist: pytest>=7.0; extra == "dev"
Requires-Dist: pytest-asyncio>=0.20; extra == "dev"
Requires-Dist: black>=22.0; extra == "dev"
Requires-Dist: flake8>=5.0; extra == "dev"
Requires-Dist: mypy>=0.990; extra == "dev"
Requires-Dist: twine>=4.0; extra == "dev"
Dynamic: author
Dynamic: home-page
Dynamic: license-file
Dynamic: requires-python
